pyfmvrp/__init__.py
pyfmvrp/env.py
pyfmvrp/engine/__init__.py
pyfmvrp/engine/city.py
pyfmvrp/engine/depot.py
pyfmvrp/engine/manager.py
pyfmvrp/engine/status.py
pyfmvrp/engine/vehicle.py
pyfmvrp/utils/__init__.py
pyfmvrp/utils/action_space.py
pyfmvrp/utils/generate_problem.py
pyfmvrp/utils/obeservation.py
pyfmvrp/utils/rewards.py
pyfmvrp/utils/visualization.py
pyfmvrp-0.0.0.0.dist-info/METADATA
pyfmvrp-0.0.0.0.dist-info/WHEEL
pyfmvrp-0.0.0.0.dist-info/top_level.txt
pyfmvrp-0.0.0.0.dist-info/RECORD
