Metadata-Version: 2.1
Name: pyfmvrp
Version: 0.0.0.0
Summary: A python flexible multi-depot VRP (FMDVRP) simulator
Home-page: UNKNOWN
Author: Junyoung park
Author-email: junyoungpark@kaist.ac.kr
License: UNKNOWN
Platform: UNKNOWN
Requires-Python: >=3.6
